GirderPatchLoad/__init__.py
GirderPatchLoad/main.py
GirderPatchLoad-1.2.0.dist-info/METADATA
GirderPatchLoad-1.2.0.dist-info/WHEEL
GirderPatchLoad-1.2.0.dist-info/top_level.txt
GirderPatchLoad-1.2.0.dist-info/RECORD
