Metadata-Version: 2.1
Name: GirderPatchLoad
Version: 1.2.0
Requires-Dist: pandas
Requires-Dist: numpy
Requires-Dist: joblib
Requires-Dist: xgboost
